ndexsignorloader/__init__.py
ndexsignorloader/loadplan.json
ndexsignorloader/ndexloadsignor.py
ndexsignorloader/style.cx
ndexsignorloader-1.2.0.data/scripts/ndexloadsignor.py
ndexsignorloader-1.2.0.dist-info/AUTHORS.rst
ndexsignorloader-1.2.0.dist-info/LICENSE
ndexsignorloader-1.2.0.dist-info/METADATA
ndexsignorloader-1.2.0.dist-info/WHEEL
ndexsignorloader-1.2.0.dist-info/top_level.txt
ndexsignorloader-1.2.0.dist-info/RECORD
