Metadata-Version: 2.1
Name: ndexsignorloader
Version: 1.2.0
Summary: Loads SIGNOR data into NDEx
Home-page: https://github.com/ndexcontent/ndexsignorloader
Author: Chris Churas
Author-email: contact@ndexbio.org
License: BSD license
Keywords: ndexsignorloader
Platform: UNKNOWN
Classifier: Development Status :: 2 - Pre-Alpha
Classifier: Intended Audience :: Developers
Classifier: License :: OSI Approved :: BSD License
Classifier: Natural Language :: English
Classifier: Programming Language :: Python :: 3.4
Classifier: Programming Language :: Python :: 3.5
Classifier: Programming Language :: Python :: 3.6
Classifier: Programming Language :: Python :: 3.7
Requires-Dist: ndex2
Requires-Dist: ndexutil
Requires-Dist: requests
Requires-Dist: pandas
